tornado_prometheus/__init__.py
tornado_prometheus-0.1.1.dist-info/LICENSE
tornado_prometheus-0.1.1.dist-info/METADATA
tornado_prometheus-0.1.1.dist-info/WHEEL
tornado_prometheus-0.1.1.dist-info/top_level.txt
tornado_prometheus-0.1.1.dist-info/RECORD
