Metadata-Version: 2.1
Name: tornado-prometheus
Version: 0.1.1
Summary: HTTP metrics for a tornado application
Home-page: https://github.com/globocom/tornado-prometheus
Author: Globo.com
Author-email: backstage@corp.globo.com
License: MIT
Keywords: prometheus tornado
Platform: UNKNOWN
Classifier: Development Status :: 4 - Beta
Classifier: Intended Audience :: Developers
Classifier: License :: OSI Approved :: MIT License
Classifier: Natural Language :: English
Classifier: Operating System :: MacOS
Classifier: Operating System :: POSIX
Classifier: Operating System :: Unix
Classifier: Operating System :: OS Independent
Classifier: Programming Language :: Python :: 2.7
Classifier: Programming Language :: Python :: 3.5
Requires-Dist: tornado (>=4.0)
Requires-Dist: prometheus-client (==0.7.1)
Provides-Extra: tests
Requires-Dist: nose ; extra == 'tests'
Requires-Dist: coverage ; extra == 'tests'
Requires-Dist: flake8 ; extra == 'tests'
